LICENSE
MANIFEST.in
README.md
setup.py
pytoml/__init__.py
pytoml/core.py
pytoml/parser.py
pytoml/test.py
pytoml/utils.py
pytoml/writer.py
pytoml.egg-info/PKG-INFO
pytoml.egg-info/SOURCES.txt
pytoml.egg-info/dependency_links.txt
pytoml.egg-info/top_level.txt
test/test.py
test/test_parser.py
test/test_writer.py