Metadata-Version: 2.1
Name: pytoml
Version: 0.1.20
Summary: A parser for TOML-0.4.0
Home-page: https://github.com/avakar/pytoml
Author: Martin Vejnár
Author-email: vejnar.martin@gmail.com
License: MIT
Platform: UNKNOWN
Classifier: Programming Language :: Python :: 2
Classifier: Programming Language :: Python :: 2.7
Classifier: Programming Language :: Python :: 3
Classifier: Programming Language :: Python :: 3.5
Classifier: Programming Language :: Python :: 3.6
Classifier: Programming Language :: Python :: 3.7
Classifier: License :: OSI Approved :: MIT License
Classifier: Topic :: Software Development :: Libraries
